pyxiver/__init__.py
pyxiver/api.py
pyxiver/core_requests.py
pyxiver/models.py
pyxiver-1.0.3.dist-info/LICENSE
pyxiver-1.0.3.dist-info/WHEEL
pyxiver-1.0.3.dist-info/METADATA
pyxiver-1.0.3.dist-info/RECORD
