Metadata-Version: 2.1
Name: pyxiver
Version: 1.0.3
Summary: Python wrapper for the arXiv.org public API.
License: MIT
Author: Neil Van
Author-email: nvq.alino@gmail.com
Requires-Python: >=3.8,<4.0
Classifier: License :: OSI Approved :: MIT License
Classifier: Programming Language :: Python :: 3
Classifier: Programming Language :: Python :: 3.8
Classifier: Programming Language :: Python :: 3.9
Requires-Dist: requests (>=2.26.0,<3.0.0)
Requires-Dist: xmltodict (>=0.12.0,<0.13.0)
